LICENSE
MANIFEST.in
README.md
fuchsia.py
setup.cfg
setup.py
bin/fuchsia
fuchsia.egg-info/PKG-INFO
fuchsia.egg-info/SOURCES.txt
fuchsia.egg-info/dependency_links.txt
fuchsia.egg-info/requires.txt
fuchsia.egg-info/top_level.txt