Metadata-Version: 1.1
Name: fuchsia
Version: 16.7.25
Summary: Fuchsia reduces differential equations for Feynman master integrals to canonical form
Home-page: http://www.gituliar.net/fuchsia/
Author: Oleksandr Gituliar, Vitaly Magerya
Author-email: oleksandr@gituliar.net
License: ISC License
Download-URL: http://gituliar.net/fuchsia/fuchsia-16.7.25.tar.gz
Keywords: differential equations,Feynman integrals
Platform: any
Classifier: Development Status :: 4 - Beta
Classifier: Intended Audience :: Science/Research
Classifier: Topic :: Scientific/Engineering :: Mathematics
Classifier: Topic :: Scientific/Engineering :: Physics
Classifier: License :: OSI Approved :: ISC License (ISCL)
Classifier: Operating System :: POSIX :: Linux
Classifier: Programming Language :: Python :: 2.7
